lpips_j/__init__.py
lpips_j/lpips.py
lpips_j-0.0.6.dist-info/LICENSE
lpips_j-0.0.6.dist-info/METADATA
lpips_j-0.0.6.dist-info/WHEEL
lpips_j-0.0.6.dist-info/top_level.txt
lpips_j-0.0.6.dist-info/RECORD
