Metadata-Version: 2.1
Name: lpips-j
Version: 0.0.6
Summary: lpips-j – Minimal JAX/Flax port of `lpips` supporting `vgg16`, with pre-trained weights stored in the 🤗 Hugging Face hub.
Home-page: https://github.com/pcuenca/lpips-j
Author: Pedro Cuenca
Author-email: pedro@latenitesoft.com
Project-URL: Bug Tracker, https://github.com/pcuenca/lpips-j/issues
Classifier: Programming Language :: Python :: 3
Classifier: License :: OSI Approved :: Apache Software License
Classifier: Operating System :: OS Independent
Classifier: Topic :: Scientific/Engineering :: Artificial Intelligence
Classifier: Development Status :: 3 - Alpha
Classifier: Intended Audience :: Developers
Requires-Python: >=3.8
License-File: LICENSE
Requires-Dist: huggingface-hub
Requires-Dist: h5py
Requires-Dist: jax
Requires-Dist: flax
Requires-Dist: flaxmodels
